{
  "collections": [{
    "name": "customerIssue",
    "nameOld": "customerIssue",
    "icon": null,
    "integration": null,
    "isReadOnly": false,
    "isSearchable": true,
    "isVirtual": false,
    "onlyForRelationships": false,
    "paginationType": "page",
    "fields": [{
      "field": "closedAt",
      "type": "Date",
      "defaultValue": null,
      "enums": null,
      "integration": null,
      "isFilterable": true,
      "isPrimaryKey": false,
      "isReadOnly": false,
      "isRequired": false,
      "isSortable": true,
      "isVirtual": false,
      "reference": null,
      "inverseOf": null,
      "validations": []
    }, {
      "field": "createdAt",
      "type": "Date",
      "defaultValue": null,
      "enums": null,
      "integration": null,
      "isFilterable": true,
      "isPrimaryKey": false,
      "isReadOnly": false,
      "isRequired": false,
      "isSortable": true,
      "isVirtual": false,
      "reference": null,
      "inverseOf": null,
      "validations": []
    }, {
      "field": "customerIssueCustomerIssueSupports",
      "type": ["Number"],
      "defaultValue": null,
      "enums": null,
      "integration": null,
      "isFilterable": true,
      "isPrimaryKey": false,
      "isReadOnly": false,
      "isRequired": false,
      "isSortable": true,
      "isVirtual": false,
      "reference": "customerIssueSupport.id",
      "inverseOf": "customerIssue",
      "relationship": "HasMany",
      "validations": []
    }, {
      "field": "customerIssueTransaction",
      "type": "Number",
      "defaultValue": null,
      "enums": null,
      "integration": null,
      "isFilterable": true,
      "isPrimaryKey": false,
      "isReadOnly": false,
      "isRequired": false,
      "isSortable": true,
      "isVirtual": false,
      "reference": "transaction.id",
      "inverseOf": "customerIssue",
      "relationship": "HasOne",
      "validations": []
    }, {
      "field": "id",
      "type": "Number",
      "defaultValue": null,
      "enums": null,
      "integration": null,
      "isFilterable": true,
      "isPrimaryKey": true,
      "isReadOnly": false,
      "isRequired": false,
      "isSortable": true,
      "isVirtual": false,
      "reference": null,
      "inverseOf": null,
      "validations": []
    }, {
      "field": "order",
      "type": "Number",
      "defaultValue": null,
      "enums": null,
      "integration": null,
      "isFilterable": true,
      "isPrimaryKey": false,
      "isReadOnly": false,
      "isRequired": false,
      "isSortable": true,
      "isVirtual": false,
      "reference": "syliusOrder.id",
      "inverseOf": "orderCustomerIssues",
      "relationship": "BelongsTo",
      "validations": []
    }, {
      "field": "owner",
      "type": "String",
      "defaultValue": null,
      "enums": null,
      "integration": null,
      "isFilterable": true,
      "isPrimaryKey": false,
      "isReadOnly": false,
      "isRequired": false,
      "isSortable": true,
      "isVirtual": false,
      "reference": null,
      "inverseOf": null,
      "validations": []
    }, {
      "field": "state",
      "type": "Enum",
      "defaultValue": null,
      "enums": [
        "open",
        "closed",
        "pending_return",
        "pending_refund",
        "refunded",
        "declined"
      ],
      "integration": null,
      "isFilterable": true,
      "isPrimaryKey": false,
      "isReadOnly": false,
      "isRequired": false,
      "isSortable": true,
      "isVirtual": false,
      "reference": null,
      "inverseOf": null,
      "validations": []
    }, {
      "field": "type",
      "type": "String",
      "defaultValue": null,
      "enums": null,
      "integration": null,
      "isFilterable": true,
      "isPrimaryKey": false,
      "isReadOnly": false,
      "isRequired": true,
      "isSortable": true,
      "isVirtual": false,
      "reference": null,
      "inverseOf": null,
      "validations": [{
        "message": null,
        "type": "is present",
        "value": null
      }]
    }, {
      "field": "updatedAt",
      "type": "Date",
      "defaultValue": null,
      "enums": null,
      "integration": null,
      "isFilterable": true,
      "isPrimaryKey": false,
      "isReadOnly": false,
      "isRequired": false,
      "isSortable": true,
      "isVirtual": false,
      "reference": null,
      "inverseOf": null,
      "validations": []
    }],
    "segments": [],
    "actions": [{
      "name": "Create support",
      "type": "single",
      "baseUrl": null,
      "endpoint": "/forest/actions/create-support",
      "httpMethod": "POST",
      "redirect": null,
      "download": false,
      "fields": [{
        "field": "type",
        "type": "Enum",
        "defaultValue": null,
        "enums": [
          "email",
          "phone",
          "chat"
        ],
        "isRequired": true,
        "reference": null,
        "description": null,
        "position": 0,
        "widget": null
      }, {
        "field": "description",
        "type": "String",
        "defaultValue": null,
        "enums": null,
        "isRequired": true,
        "reference": null,
        "description": null,
        "position": 1,
        "widget": "text area"
      }],
      "hooks": {
        "load": false,
        "change": []
      }
    }, {
      "name": "Issue solved",
      "type": "bulk",
      "baseUrl": null,
      "endpoint": "/forest/actions/issue-solved",
      "httpMethod": "POST",
      "redirect": null,
      "download": false,
      "fields": [],
      "hooks": {
        "load": false,
        "change": []
      }
    }]
  }, {
    "name": "customerIssueSupport",
    "nameOld": "customerIssueSupport",
    "icon": null,
    "integration": null,
    "isReadOnly": false,
    "isSearchable": true,
    "isVirtual": false,
    "onlyForRelationships": false,
    "paginationType": "page",
    "fields": [{
      "field": "createdAt",
      "type": "Date",
      "defaultValue": null,
      "enums": null,
      "integration": null,
      "isFilterable": true,
      "isPrimaryKey": false,
      "isReadOnly": false,
      "isRequired": false,
      "isSortable": true,
      "isVirtual": false,
      "reference": null,
      "inverseOf": null,
      "validations": []
    }, {
      "field": "customerIssue",
      "type": "Number",
      "defaultValue": null,
      "enums": null,
      "integration": null,
      "isFilterable": true,
      "isPrimaryKey": false,
      "isReadOnly": false,
      "isRequired": false,
      "isSortable": true,
      "isVirtual": false,
      "reference": "customerIssue.id",
      "inverseOf": "customerIssueCustomerIssueSupports",
      "relationship": "BelongsTo",
      "validations": []
    }, {
      "field": "description",
      "type": "String",
      "defaultValue": null,
      "enums": null,
      "integration": null,
      "isFilterable": true,
      "isPrimaryKey": false,
      "isReadOnly": false,
      "isRequired": false,
      "isSortable": true,
      "isVirtual": false,
      "reference": null,
      "inverseOf": null,
      "validations": []
    }, {
      "field": "id",
      "type": "Number",
      "defaultValue": null,
      "enums": null,
      "integration": null,
      "isFilterable": true,
      "isPrimaryKey": true,
      "isReadOnly": false,
      "isRequired": false,
      "isSortable": true,
      "isVirtual": false,
      "reference": null,
      "inverseOf": null,
      "validations": []
    }, {
      "field": "owner",
      "type": "String",
      "defaultValue": null,
      "enums": null,
      "integration": null,
      "isFilterable": true,
      "isPrimaryKey": false,
      "isReadOnly": false,
      "isRequired": false,
      "isSortable": true,
      "isVirtual": false,
      "reference": null,
      "inverseOf": null,
      "validations": []
    }, {
      "field": "type",
      "type": "String",
      "defaultValue": null,
      "enums": null,
      "integration": null,
      "isFilterable": true,
      "isPrimaryKey": false,
      "isReadOnly": false,
      "isRequired": true,
      "isSortable": true,
      "isVirtual": false,
      "reference": null,
      "inverseOf": null,
      "validations": [{
        "message": null,
        "type": "is present",
        "value": null
      }]
    }, {
      "field": "updatedAt",
      "type": "Date",
      "defaultValue": null,
      "enums": null,
      "integration": null,
      "isFilterable": true,
      "isPrimaryKey": false,
      "isReadOnly": false,
      "isRequired": false,
      "isSortable": true,
      "isVirtual": false,
      "reference": null,
      "inverseOf": null,
      "validations": []
    }],
    "segments": [],
    "actions": []
  }, {
    "name": "storageUnit",
    "nameOld": "storageUnit",
    "icon": null,
    "integration": null,
    "isReadOnly": false,
    "isSearchable": true,
    "isVirtual": false,
    "onlyForRelationships": false,
    "paginationType": "page",
    "fields": [{
      "field": "aisle",
      "type": "String",
      "defaultValue": null,
      "enums": null,
      "integration": null,
      "isFilterable": true,
      "isPrimaryKey": false,
      "isReadOnly": false,
      "isRequired": false,
      "isSortable": true,
      "isVirtual": false,
      "reference": null,
      "inverseOf": null,
      "validations": []
    }, {
      "field": "box",
      "type": "String",
      "defaultValue": null,
      "enums": null,
      "integration": null,
      "isFilterable": true,
      "isPrimaryKey": false,
      "isReadOnly": false,
      "isRequired": true,
      "isSortable": true,
      "isVirtual": false,
      "reference": null,
      "inverseOf": null,
      "validations": [{
        "message": null,
        "type": "is present",
        "value": null
      }]
    }, {
      "field": "createdAt",
      "type": "Date",
      "defaultValue": null,
      "enums": null,
      "integration": null,
      "isFilterable": true,
      "isPrimaryKey": false,
      "isReadOnly": false,
      "isRequired": false,
      "isSortable": true,
      "isVirtual": false,
      "reference": null,
      "inverseOf": null,
      "validations": []
    }, {
      "field": "deletedAt",
      "type": "Date",
      "defaultValue": null,
      "enums": null,
      "integration": null,
      "isFilterable": true,
      "isPrimaryKey": false,
      "isReadOnly": false,
      "isRequired": false,
      "isSortable": true,
      "isVirtual": false,
      "reference": null,
      "inverseOf": null,
      "validations": []
    }, {
      "field": "id",
      "type": "Number",
      "defaultValue": null,
      "enums": null,
      "integration": null,
      "isFilterable": true,
      "isPrimaryKey": true,
      "isReadOnly": false,
      "isRequired": false,
      "isSortable": true,
      "isVirtual": false,
      "reference": null,
      "inverseOf": null,
      "validations": []
    }, {
      "field": "isFlagged",
      "type": "Number",
      "defaultValue": null,
      "enums": null,
      "integration": null,
      "isFilterable": true,
      "isPrimaryKey": false,
      "isReadOnly": false,
      "isRequired": true,
      "isSortable": true,
      "isVirtual": false,
      "reference": null,
      "inverseOf": null,
      "validations": [{
        "message": null,
        "type": "is present",
        "value": null
      }]
    }, {
      "field": "product",
      "type": "Number",
      "defaultValue": null,
      "enums": null,
      "integration": null,
      "isFilterable": true,
      "isPrimaryKey": false,
      "isReadOnly": false,
      "isRequired": false,
      "isSortable": true,
      "isVirtual": false,
      "reference": "syliusProduct.id",
      "inverseOf": "productStorageUnits",
      "relationship": "BelongsTo",
      "validations": []
    }, {
      "field": "quantity",
      "type": "Number",
      "defaultValue": null,
      "enums": null,
      "integration": null,
      "isFilterable": true,
      "isPrimaryKey": false,
      "isReadOnly": false,
      "isRequired": true,
      "isSortable": true,
      "isVirtual": false,
      "reference": null,
      "inverseOf": null,
      "validations": [{
        "message": null,
        "type": "is present",
        "value": null
      }]
    }, {
      "field": "row",
      "type": "String",
      "defaultValue": null,
      "enums": null,
      "integration": null,
      "isFilterable": true,
      "isPrimaryKey": false,
      "isReadOnly": false,
      "isRequired": true,
      "isSortable": true,
      "isVirtual": false,
      "reference": null,
      "inverseOf": null,
      "validations": [{
        "message": null,
        "type": "is present",
        "value": null
      }]
    }, {
      "field": "storageType",
      "type": "Enum",
      "defaultValue": null,
      "enums": [
        "free",
        "bags",
        "boxes",
        "palets"
      ],
      "integration": null,
      "isFilterable": true,
      "isPrimaryKey": false,
      "isReadOnly": false,
      "isRequired": true,
      "isSortable": true,
      "isVirtual": false,
      "reference": null,
      "inverseOf": null,
      "validations": [{
        "message": null,
        "type": "is present",
        "value": null
      }]
    }, {
      "field": "updatedAt",
      "type": "Date",
      "defaultValue": null,
      "enums": null,
      "integration": null,
      "isFilterable": true,
      "isPrimaryKey": false,
      "isReadOnly": false,
      "isRequired": false,
      "isSortable": true,
      "isVirtual": false,
      "reference": null,
      "inverseOf": null,
      "validations": []
    }, {
      "field": "warehouse",
      "type": "Number",
      "defaultValue": null,
      "enums": null,
      "integration": null,
      "isFilterable": true,
      "isPrimaryKey": false,
      "isReadOnly": false,
      "isRequired": false,
      "isSortable": true,
      "isVirtual": false,
      "reference": "warehouse.id",
      "inverseOf": "storageUnits",
      "relationship": "BelongsTo",
      "validations": []
    }],
    "segments": [],
    "actions": []
  }, {
    "name": "syliusAddress",
    "nameOld": "syliusAddress",
    "icon": null,
    "integration": null,
    "isReadOnly": false,
    "isSearchable": true,
    "isVirtual": false,
    "onlyForRelationships": false,
    "paginationType": "page",
    "fields": [{
      "field": "city",
      "type": "String",
      "defaultValue": null,
      "enums": null,
      "integration": null,
      "isFilterable": true,
      "isPrimaryKey": false,
      "isReadOnly": false,
      "isRequired": true,
      "isSortable": true,
      "isVirtual": false,
      "reference": null,
      "inverseOf": null,
      "validations": [{
        "message": null,
        "type": "is present",
        "value": null
      }]
    }, {
      "field": "company",
      "type": "String",
      "defaultValue": null,
      "enums": null,
      "integration": null,
      "isFilterable": true,
      "isPrimaryKey": false,
      "isReadOnly": false,
      "isRequired": false,
      "isSortable": true,
      "isVirtual": false,
      "reference": null,
      "inverseOf": null,
      "validations": []
    }, {
      "field": "countryCode",
      "type": "String",
      "defaultValue": null,
      "enums": null,
      "integration": null,
      "isFilterable": true,
      "isPrimaryKey": false,
      "isReadOnly": false,
      "isRequired": true,
      "isSortable": true,
      "isVirtual": false,
      "reference": null,
      "inverseOf": null,
      "validations": [{
        "message": null,
        "type": "is present",
        "value": null
      }]
    }, {
      "field": "customer",
      "type": "Number",
      "defaultValue": null,
      "enums": null,
      "integration": null,
      "isFilterable": true,
      "isPrimaryKey": false,
      "isReadOnly": false,
      "isRequired": false,
      "isSortable": true,
      "isVirtual": false,
      "reference": "syliusCustomer.id",
      "inverseOf": "customerSyliusAddresses",
      "relationship": "BelongsTo",
      "validations": []
    }, {
      "field": "firstName",
      "type": "String",
      "defaultValue": null,
      "enums": null,
      "integration": null,
      "isFilterable": true,
      "isPrimaryKey": false,
      "isReadOnly": false,
      "isRequired": true,
      "isSortable": true,
      "isVirtual": false,
      "reference": null,
      "inverseOf": null,
      "validations": [{
        "message": null,
        "type": "is present",
        "value": null
      }]
    }, {
      "field": "id",
      "type": "Number",
      "defaultValue": null,
      "enums": null,
      "integration": null,
      "isFilterable": true,
      "isPrimaryKey": true,
      "isReadOnly": false,
      "isRequired": false,
      "isSortable": true,
      "isVirtual": false,
      "reference": null,
      "inverseOf": null,
      "validations": []
    }, {
      "field": "lastName",
      "type": "String",
      "defaultValue": null,
      "enums": null,
      "integration": null,
      "isFilterable": true,
      "isPrimaryKey": false,
      "isReadOnly": false,
      "isRequired": true,
      "isSortable": true,
      "isVirtual": false,
      "reference": null,
      "inverseOf": null,
      "validations": [{
        "message": null,
        "type": "is present",
        "value": null
      }]
    }, {
      "field": "phoneNumber",
      "type": "String",
      "defaultValue": null,
      "enums": null,
      "integration": null,
      "isFilterable": true,
      "isPrimaryKey": false,
      "isReadOnly": false,
      "isRequired": false,
      "isSortable": true,
      "isVirtual": false,
      "reference": null,
      "inverseOf": null,
      "validations": []
    }, {
      "field": "postcode",
      "type": "String",
      "defaultValue": null,
      "enums": null,
      "integration": null,
      "isFilterable": true,
      "isPrimaryKey": false,
      "isReadOnly": false,
      "isRequired": true,
      "isSortable": true,
      "isVirtual": false,
      "reference": null,
      "inverseOf": null,
      "validations": [{
        "message": null,
        "type": "is present",
        "value": null
      }]
    }, {
      "field": "street",
      "type": "String",
      "defaultValue": null,
      "enums": null,
      "integration": null,
      "isFilterable": true,
      "isPrimaryKey": false,
      "isReadOnly": false,
      "isRequired": true,
      "isSortable": true,
      "isVirtual": false,
      "reference": null,
      "inverseOf": null,
      "validations": [{
        "message": null,
        "type": "is present",
        "value": null
      }]
    }],
    "segments": [],
    "actions": []
  }, {
    "name": "syliusCustomer",
    "nameOld": "syliusCustomer",
    "icon": null,
    "integration": null,
    "isReadOnly": false,
    "isSearchable": true,
    "isVirtual": false,
    "onlyForRelationships": false,
    "paginationType": "page",
    "fields": [{
      "field": "birthday",
      "type": "Dateonly",
      "defaultValue": null,
      "enums": null,
      "integration": null,
      "isFilterable": true,
      "isPrimaryKey": false,
      "isReadOnly": false,
      "isRequired": false,
      "isSortable": true,
      "isVirtual": false,
      "reference": null,
      "inverseOf": null,
      "validations": []
    }, {
      "field": "company",
      "type": "String",
      "defaultValue": null,
      "enums": null,
      "integration": null,
      "isFilterable": true,
      "isPrimaryKey": false,
      "isReadOnly": false,
      "isRequired": false,
      "isSortable": true,
      "isVirtual": false,
      "reference": null,
      "inverseOf": null,
      "validations": []
    }, {
      "field": "createdAt",
      "type": "Date",
      "defaultValue": null,
      "enums": null,
      "integration": null,
      "isFilterable": true,
      "isPrimaryKey": false,
      "isReadOnly": false,
      "isRequired": false,
      "isSortable": true,
      "isVirtual": false,
      "reference": null,
      "inverseOf": null,
      "validations": []
    }, {
      "field": "customerSyliusAddresses",
      "type": ["Number"],
      "defaultValue": null,
      "enums": null,
      "integration": null,
      "isFilterable": true,
      "isPrimaryKey": false,
      "isReadOnly": false,
      "isRequired": false,
      "isSortable": true,
      "isVirtual": false,
      "reference": "syliusAddress.id",
      "inverseOf": "customer",
      "relationship": "HasMany",
      "validations": []
    }, {
      "field": "customerSyliusOrders",
      "type": ["Number"],
      "defaultValue": null,
      "enums": null,
      "integration": null,
      "isFilterable": true,
      "isPrimaryKey": false,
      "isReadOnly": false,
      "isRequired": false,
      "isSortable": true,
      "isVirtual": false,
      "reference": "syliusOrder.id",
      "inverseOf": "customer",
      "relationship": "HasMany",
      "validations": []
    }, {
      "field": "email",
      "type": "String",
      "defaultValue": null,
      "enums": null,
      "integration": null,
      "isFilterable": true,
      "isPrimaryKey": false,
      "isReadOnly": false,
      "isRequired": true,
      "isSortable": true,
      "isVirtual": false,
      "reference": null,
      "inverseOf": null,
      "validations": [{
        "message": null,
        "type": "is present",
        "value": null
      }]
    }, {
      "field": "firstName",
      "type": "String",
      "defaultValue": null,
      "enums": null,
      "integration": null,
      "isFilterable": true,
      "isPrimaryKey": false,
      "isReadOnly": false,
      "isRequired": true,
      "isSortable": true,
      "isVirtual": false,
      "reference": null,
      "inverseOf": null,
      "validations": [{
        "message": null,
        "type": "is present",
        "value": null
      }]
    }, {
      "field": "gender",
      "type": "String",
      "defaultValue": null,
      "enums": null,
      "integration": null,
      "isFilterable": true,
      "isPrimaryKey": false,
      "isReadOnly": false,
      "isRequired": false,
      "isSortable": true,
      "isVirtual": false,
      "reference": null,
      "inverseOf": null,
      "validations": []
    }, {
      "field": "id",
      "type": "Number",
      "defaultValue": null,
      "enums": null,
      "integration": null,
      "isFilterable": true,
      "isPrimaryKey": true,
      "isReadOnly": false,
      "isRequired": false,
      "isSortable": true,
      "isVirtual": false,
      "reference": null,
      "inverseOf": null,
      "validations": []
    }, {
      "field": "lastName",
      "type": "String",
      "defaultValue": null,
      "enums": null,
      "integration": null,
      "isFilterable": true,
      "isPrimaryKey": false,
      "isReadOnly": false,
      "isRequired": true,
      "isSortable": true,
      "isVirtual": false,
      "reference": null,
      "inverseOf": null,
      "validations": [{
        "message": null,
        "type": "is present",
        "value": null
      }]
    }, {
      "field": "updatedAt",
      "type": "Date",
      "defaultValue": null,
      "enums": null,
      "integration": null,
      "isFilterable": true,
      "isPrimaryKey": false,
      "isReadOnly": false,
      "isRequired": false,
      "isSortable": true,
      "isVirtual": false,
      "reference": null,
      "inverseOf": null,
      "validations": []
    }],
    "segments": [],
    "actions": []
  }, {
    "name": "syliusOrder",
    "nameOld": "syliusOrder",
    "icon": null,
    "integration": null,
    "isReadOnly": false,
    "isSearchable": true,
    "isVirtual": false,
    "onlyForRelationships": false,
    "paginationType": "page",
    "fields": [{
      "field": "createdAt",
      "type": "Date",
      "defaultValue": null,
      "enums": null,
      "integration": null,
      "isFilterable": true,
      "isPrimaryKey": false,
      "isReadOnly": false,
      "isRequired": false,
      "isSortable": true,
      "isVirtual": false,
      "reference": null,
      "inverseOf": null,
      "validations": []
    }, {
      "field": "customer",
      "type": "Number",
      "defaultValue": null,
      "enums": null,
      "integration": null,
      "isFilterable": true,
      "isPrimaryKey": false,
      "isReadOnly": false,
      "isRequired": false,
      "isSortable": true,
      "isVirtual": false,
      "reference": "syliusCustomer.id",
      "inverseOf": "customerSyliusOrders",
      "relationship": "BelongsTo",
      "validations": []
    }, {
      "field": "id",
      "type": "Number",
      "defaultValue": null,
      "enums": null,
      "integration": null,
      "isFilterable": true,
      "isPrimaryKey": true,
      "isReadOnly": false,
      "isRequired": false,
      "isSortable": true,
      "isVirtual": false,
      "reference": null,
      "inverseOf": null,
      "validations": []
    }, {
      "field": "number",
      "type": "String",
      "defaultValue": null,
      "enums": null,
      "integration": null,
      "isFilterable": true,
      "isPrimaryKey": false,
      "isReadOnly": false,
      "isRequired": true,
      "isSortable": true,
      "isVirtual": false,
      "reference": null,
      "inverseOf": null,
      "validations": [{
        "message": null,
        "type": "is present",
        "value": null
      }]
    }, {
      "field": "orderCustomerIssues",
      "type": ["Number"],
      "defaultValue": null,
      "enums": null,
      "integration": null,
      "isFilterable": true,
      "isPrimaryKey": false,
      "isReadOnly": false,
      "isRequired": false,
      "isSortable": true,
      "isVirtual": false,
      "reference": "customerIssue.id",
      "inverseOf": "order",
      "relationship": "HasMany",
      "validations": []
    }, {
      "field": "orderSyliusOrderItems",
      "type": ["Number"],
      "defaultValue": null,
      "enums": null,
      "integration": null,
      "isFilterable": true,
      "isPrimaryKey": false,
      "isReadOnly": false,
      "isRequired": false,
      "isSortable": true,
      "isVirtual": false,
      "reference": "syliusOrderItem.id",
      "inverseOf": "order",
      "relationship": "HasMany",
      "validations": []
    }, {
      "field": "orderSyliusPayments",
      "type": ["Number"],
      "defaultValue": null,
      "enums": null,
      "integration": null,
      "isFilterable": true,
      "isPrimaryKey": false,
      "isReadOnly": false,
      "isRequired": false,
      "isSortable": true,
      "isVirtual": false,
      "reference": "syliusPayment.id",
      "inverseOf": "order",
      "relationship": "HasMany",
      "validations": []
    }, {
      "field": "orderSyliusShippings",
      "type": ["Number"],
      "defaultValue": null,
      "enums": null,
      "integration": null,
      "isFilterable": true,
      "isPrimaryKey": false,
      "isReadOnly": false,
      "isRequired": false,
      "isSortable": true,
      "isVirtual": false,
      "reference": "syliusShipping.id",
      "inverseOf": "order",
      "relationship": "HasMany",
      "validations": []
    }, {
      "field": "orderTransaction",
      "type": "Number",
      "defaultValue": null,
      "enums": null,
      "integration": null,
      "isFilterable": true,
      "isPrimaryKey": false,
      "isReadOnly": false,
      "isRequired": false,
      "isSortable": true,
      "isVirtual": false,
      "reference": "transaction.id",
      "inverseOf": "order",
      "relationship": "HasOne",
      "validations": []
    }, {
      "field": "owner",
      "type": "String",
      "defaultValue": null,
      "enums": null,
      "integration": null,
      "isFilterable": true,
      "isPrimaryKey": false,
      "isReadOnly": false,
      "isRequired": false,
      "isSortable": true,
      "isVirtual": false,
      "reference": null,
      "inverseOf": null,
      "validations": []
    }, {
      "field": "state",
      "type": "Enum",
      "defaultValue": null,
      "enums": [
        "New",
        "Fulfilled",
        "Blocked"
      ],
      "integration": null,
      "isFilterable": true,
      "isPrimaryKey": false,
      "isReadOnly": false,
      "isRequired": false,
      "isSortable": true,
      "isVirtual": false,
      "reference": null,
      "inverseOf": null,
      "validations": []
    }, {
      "field": "total",
      "type": "Number",
      "defaultValue": null,
      "enums": null,
      "integration": null,
      "isFilterable": true,
      "isPrimaryKey": false,
      "isReadOnly": false,
      "isRequired": true,
      "isSortable": true,
      "isVirtual": false,
      "reference": null,
      "inverseOf": null,
      "validations": [{
        "message": null,
        "type": "is present",
        "value": null
      }]
    }, {
      "field": "updatedAt",
      "type": "Date",
      "defaultValue": null,
      "enums": null,
      "integration": null,
      "isFilterable": true,
      "isPrimaryKey": false,
      "isReadOnly": false,
      "isRequired": false,
      "isSortable": true,
      "isVirtual": false,
      "reference": null,
      "inverseOf": null,
      "validations": []
    }],
    "segments": [],
    "actions": [{
      "name": "Mark as Fulfilled",
      "type": "bulk",
      "baseUrl": null,
      "endpoint": "/forest/actions/mark-as-fulfilled",
      "httpMethod": "POST",
      "redirect": null,
      "download": false,
      "fields": [],
      "hooks": {
        "load": false,
        "change": []
      }
    }, {
      "name": "Payment issue",
      "type": "single",
      "baseUrl": null,
      "endpoint": "/forest/actions/payment-issue",
      "httpMethod": "POST",
      "redirect": null,
      "download": false,
      "fields": [],
      "hooks": {
        "load": false,
        "change": []
      }
    }, {
      "name": "Return issue",
      "type": "single",
      "baseUrl": null,
      "endpoint": "/forest/actions/return-issue",
      "httpMethod": "POST",
      "redirect": null,
      "download": false,
      "fields": [],
      "hooks": {
        "load": false,
        "change": []
      }
    }, {
      "name": "Shipping issue",
      "type": "single",
      "baseUrl": null,
      "endpoint": "/forest/actions/shipping-issue",
      "httpMethod": "POST",
      "redirect": null,
      "download": false,
      "fields": [],
      "hooks": {
        "load": false,
        "change": []
      }
    }]
  }, {
    "name": "syliusOrderItem",
    "nameOld": "syliusOrderItem",
    "icon": null,
    "integration": null,
    "isReadOnly": false,
    "isSearchable": true,
    "isVirtual": false,
    "onlyForRelationships": false,
    "paginationType": "page",
    "fields": [{
      "field": "id",
      "type": "Number",
      "defaultValue": null,
      "enums": null,
      "integration": null,
      "isFilterable": true,
      "isPrimaryKey": true,
      "isReadOnly": false,
      "isRequired": false,
      "isSortable": true,
      "isVirtual": false,
      "reference": null,
      "inverseOf": null,
      "validations": []
    }, {
      "field": "order",
      "type": "Number",
      "defaultValue": null,
      "enums": null,
      "integration": null,
      "isFilterable": true,
      "isPrimaryKey": false,
      "isReadOnly": false,
      "isRequired": false,
      "isSortable": true,
      "isVirtual": false,
      "reference": "syliusOrder.id",
      "inverseOf": "orderSyliusOrderItems",
      "relationship": "BelongsTo",
      "validations": []
    }, {
      "field": "product",
      "type": "Number",
      "defaultValue": null,
      "enums": null,
      "integration": null,
      "isFilterable": true,
      "isPrimaryKey": false,
      "isReadOnly": false,
      "isRequired": false,
      "isSortable": true,
      "isVirtual": false,
      "reference": "syliusProduct.id",
      "inverseOf": "productSyliusOrderItems",
      "relationship": "BelongsTo",
      "validations": []
    }, {
      "field": "quantity",
      "type": "Number",
      "defaultValue": null,
      "enums": null,
      "integration": null,
      "isFilterable": true,
      "isPrimaryKey": false,
      "isReadOnly": false,
      "isRequired": true,
      "isSortable": true,
      "isVirtual": false,
      "reference": null,
      "inverseOf": null,
      "validations": [{
        "message": null,
        "type": "is present",
        "value": null
      }]
    }, {
      "field": "total",
      "type": "Number",
      "defaultValue": null,
      "enums": null,
      "integration": null,
      "isFilterable": true,
      "isPrimaryKey": false,
      "isReadOnly": false,
      "isRequired": true,
      "isSortable": true,
      "isVirtual": false,
      "reference": null,
      "inverseOf": null,
      "validations": [{
        "message": null,
        "type": "is present",
        "value": null
      }]
    }, {
      "field": "unitPrice",
      "type": "Number",
      "defaultValue": null,
      "enums": null,
      "integration": null,
      "isFilterable": true,
      "isPrimaryKey": false,
      "isReadOnly": false,
      "isRequired": true,
      "isSortable": true,
      "isVirtual": false,
      "reference": null,
      "inverseOf": null,
      "validations": [{
        "message": null,
        "type": "is present",
        "value": null
      }]
    }],
    "segments": [],
    "actions": []
  }, {
    "name": "syliusPayment",
    "nameOld": "syliusPayment",
    "icon": null,
    "integration": null,
    "isReadOnly": false,
    "isSearchable": true,
    "isVirtual": false,
    "onlyForRelationships": false,
    "paginationType": "page",
    "fields": [{
      "field": "amount",
      "type": "Number",
      "defaultValue": null,
      "enums": null,
      "integration": null,
      "isFilterable": true,
      "isPrimaryKey": false,
      "isReadOnly": false,
      "isRequired": true,
      "isSortable": true,
      "isVirtual": false,
      "reference": null,
      "inverseOf": null,
      "validations": [{
        "message": null,
        "type": "is present",
        "value": null
      }]
    }, {
      "field": "currencyCode",
      "type": "String",
      "defaultValue": null,
      "enums": null,
      "integration": null,
      "isFilterable": true,
      "isPrimaryKey": false,
      "isReadOnly": false,
      "isRequired": true,
      "isSortable": true,
      "isVirtual": false,
      "reference": null,
      "inverseOf": null,
      "validations": [{
        "message": null,
        "type": "is present",
        "value": null
      }]
    }, {
      "field": "details",
      "type": "String",
      "defaultValue": null,
      "enums": null,
      "integration": null,
      "isFilterable": true,
      "isPrimaryKey": false,
      "isReadOnly": false,
      "isRequired": false,
      "isSortable": true,
      "isVirtual": false,
      "reference": null,
      "inverseOf": null,
      "validations": []
    }, {
      "field": "id",
      "type": "Number",
      "defaultValue": null,
      "enums": null,
      "integration": null,
      "isFilterable": true,
      "isPrimaryKey": true,
      "isReadOnly": false,
      "isRequired": false,
      "isSortable": true,
      "isVirtual": false,
      "reference": null,
      "inverseOf": null,
      "validations": []
    }, {
      "field": "method",
      "type": "Number",
      "defaultValue": null,
      "enums": null,
      "integration": null,
      "isFilterable": true,
      "isPrimaryKey": false,
      "isReadOnly": false,
      "isRequired": false,
      "isSortable": true,
      "isVirtual": false,
      "reference": "syliusPaymentMethod.id",
      "inverseOf": "methodSyliusPayments",
      "relationship": "BelongsTo",
      "validations": []
    }, {
      "field": "order",
      "type": "Number",
      "defaultValue": null,
      "enums": null,
      "integration": null,
      "isFilterable": true,
      "isPrimaryKey": false,
      "isReadOnly": false,
      "isRequired": false,
      "isSortable": true,
      "isVirtual": false,
      "reference": "syliusOrder.id",
      "inverseOf": "orderSyliusPayments",
      "relationship": "BelongsTo",
      "validations": []
    }, {
      "field": "state",
      "type": "String",
      "defaultValue": null,
      "enums": null,
      "integration": null,
      "isFilterable": true,
      "isPrimaryKey": false,
      "isReadOnly": false,
      "isRequired": true,
      "isSortable": true,
      "isVirtual": false,
      "reference": null,
      "inverseOf": null,
      "validations": [{
        "message": null,
        "type": "is present",
        "value": null
      }]
    }],
    "segments": [],
    "actions": []
  }, {
    "name": "syliusPaymentMethod",
    "nameOld": "syliusPaymentMethod",
    "icon": null,
    "integration": null,
    "isReadOnly": false,
    "isSearchable": true,
    "isVirtual": false,
    "onlyForRelationships": false,
    "paginationType": "page",
    "fields": [{
      "field": "code",
      "type": "String",
      "defaultValue": null,
      "enums": null,
      "integration": null,
      "isFilterable": true,
      "isPrimaryKey": false,
      "isReadOnly": false,
      "isRequired": true,
      "isSortable": true,
      "isVirtual": false,
      "reference": null,
      "inverseOf": null,
      "validations": [{
        "message": null,
        "type": "is present",
        "value": null
      }]
    }, {
      "field": "createdAt",
      "type": "Date",
      "defaultValue": null,
      "enums": null,
      "integration": null,
      "isFilterable": true,
      "isPrimaryKey": false,
      "isReadOnly": false,
      "isRequired": false,
      "isSortable": true,
      "isVirtual": false,
      "reference": null,
      "inverseOf": null,
      "validations": []
    }, {
      "field": "description",
      "type": "String",
      "defaultValue": null,
      "enums": null,
      "integration": null,
      "isFilterable": true,
      "isPrimaryKey": false,
      "isReadOnly": false,
      "isRequired": false,
      "isSortable": true,
      "isVirtual": false,
      "reference": null,
      "inverseOf": null,
      "validations": []
    }, {
      "field": "enabled",
      "type": "Number",
      "defaultValue": null,
      "enums": null,
      "integration": null,
      "isFilterable": true,
      "isPrimaryKey": false,
      "isReadOnly": false,
      "isRequired": true,
      "isSortable": true,
      "isVirtual": false,
      "reference": null,
      "inverseOf": null,
      "validations": [{
        "message": null,
        "type": "is present",
        "value": null
      }]
    }, {
      "field": "id",
      "type": "Number",
      "defaultValue": null,
      "enums": null,
      "integration": null,
      "isFilterable": true,
      "isPrimaryKey": true,
      "isReadOnly": false,
      "isRequired": false,
      "isSortable": true,
      "isVirtual": false,
      "reference": null,
      "inverseOf": null,
      "validations": []
    }, {
      "field": "methodSyliusPayments",
      "type": ["Number"],
      "defaultValue": null,
      "enums": null,
      "integration": null,
      "isFilterable": true,
      "isPrimaryKey": false,
      "isReadOnly": false,
      "isRequired": false,
      "isSortable": true,
      "isVirtual": false,
      "reference": "syliusPayment.id",
      "inverseOf": "method",
      "relationship": "HasMany",
      "validations": []
    }, {
      "field": "name",
      "type": "String",
      "defaultValue": null,
      "enums": null,
      "integration": null,
      "isFilterable": true,
      "isPrimaryKey": false,
      "isReadOnly": false,
      "isRequired": true,
      "isSortable": true,
      "isVirtual": false,
      "reference": null,
      "inverseOf": null,
      "validations": [{
        "message": null,
        "type": "is present",
        "value": null
      }]
    }, {
      "field": "updatedAt",
      "type": "Date",
      "defaultValue": null,
      "enums": null,
      "integration": null,
      "isFilterable": true,
      "isPrimaryKey": false,
      "isReadOnly": false,
      "isRequired": false,
      "isSortable": true,
      "isVirtual": false,
      "reference": null,
      "inverseOf": null,
      "validations": []
    }],
    "segments": [],
    "actions": []
  }, {
    "name": "syliusProduct",
    "nameOld": "syliusProduct",
    "icon": null,
    "integration": null,
    "isReadOnly": false,
    "isSearchable": true,
    "isVirtual": false,
    "onlyForRelationships": false,
    "paginationType": "page",
    "fields": [{
      "field": "brand",
      "type": "String",
      "defaultValue": null,
      "enums": null,
      "integration": null,
      "isFilterable": true,
      "isPrimaryKey": false,
      "isReadOnly": false,
      "isRequired": true,
      "isSortable": true,
      "isVirtual": false,
      "reference": null,
      "inverseOf": null,
      "validations": [{
        "message": null,
        "type": "is present",
        "value": null
      }]
    }, {
      "field": "description",
      "type": "String",
      "defaultValue": null,
      "enums": null,
      "integration": null,
      "isFilterable": true,
      "isPrimaryKey": false,
      "isReadOnly": false,
      "isRequired": false,
      "isSortable": true,
      "isVirtual": false,
      "reference": null,
      "inverseOf": null,
      "validations": []
    }, {
      "field": "id",
      "type": "Number",
      "defaultValue": null,
      "enums": null,
      "integration": null,
      "isFilterable": true,
      "isPrimaryKey": true,
      "isReadOnly": false,
      "isRequired": false,
      "isSortable": true,
      "isVirtual": false,
      "reference": null,
      "inverseOf": null,
      "validations": []
    }, {
      "field": "imagePath",
      "type": "String",
      "defaultValue": null,
      "enums": null,
      "integration": null,
      "isFilterable": true,
      "isPrimaryKey": false,
      "isReadOnly": false,
      "isRequired": false,
      "isSortable": true,
      "isVirtual": false,
      "reference": null,
      "inverseOf": null,
      "validations": []
    }, {
      "field": "name",
      "type": "String",
      "defaultValue": null,
      "enums": null,
      "integration": null,
      "isFilterable": true,
      "isPrimaryKey": false,
      "isReadOnly": false,
      "isRequired": true,
      "isSortable": true,
      "isVirtual": false,
      "reference": null,
      "inverseOf": null,
      "validations": [{
        "message": null,
        "type": "is present",
        "value": null
      }]
    }, {
      "field": "price",
      "type": "Number",
      "defaultValue": null,
      "enums": null,
      "integration": null,
      "isFilterable": true,
      "isPrimaryKey": false,
      "isReadOnly": false,
      "isRequired": true,
      "isSortable": true,
      "isVirtual": false,
      "reference": null,
      "inverseOf": null,
      "validations": [{
        "message": null,
        "type": "is present",
        "value": null
      }]
    }, {
      "field": "productStorageUnits",
      "type": ["Number"],
      "defaultValue": null,
      "enums": null,
      "integration": null,
      "isFilterable": true,
      "isPrimaryKey": false,
      "isReadOnly": false,
      "isRequired": false,
      "isSortable": true,
      "isVirtual": false,
      "reference": "storageUnit.id",
      "inverseOf": "product",
      "relationship": "HasMany",
      "validations": []
    }, {
      "field": "productSyliusOrderItems",
      "type": ["Number"],
      "defaultValue": null,
      "enums": null,
      "integration": null,
      "isFilterable": true,
      "isPrimaryKey": false,
      "isReadOnly": false,
      "isRequired": false,
      "isSortable": true,
      "isVirtual": false,
      "reference": "syliusOrderItem.id",
      "inverseOf": "product",
      "relationship": "HasMany",
      "validations": []
    }, {
      "field": "productSyliusProductVariants",
      "type": ["Number"],
      "defaultValue": null,
      "enums": null,
      "integration": null,
      "isFilterable": true,
      "isPrimaryKey": false,
      "isReadOnly": false,
      "isRequired": false,
      "isSortable": true,
      "isVirtual": false,
      "reference": "syliusProductVariant.id",
      "inverseOf": "product",
      "relationship": "HasMany",
      "validations": []
    }, {
      "field": "status",
      "type": "Enum",
      "defaultValue": null,
      "enums": ["available", "out-of-stock"],
      "integration": null,
      "isFilterable": true,
      "isPrimaryKey": false,
      "isReadOnly": false,
      "isRequired": true,
      "isSortable": true,
      "isVirtual": false,
      "reference": null,
      "inverseOf": null,
      "validations": [{
        "message": null,
        "type": "is present",
        "value": null
      }]
    }, {
      "field": "syliusTaxonThroughSyliusProductTaxons",
      "type": ["Number"],
      "defaultValue": null,
      "enums": null,
      "integration": null,
      "isFilterable": true,
      "isPrimaryKey": false,
      "isReadOnly": false,
      "isRequired": false,
      "isSortable": true,
      "isVirtual": false,
      "reference": "syliusTaxon.id",
      "inverseOf": "syliusProductThroughSyliusProductTaxons",
      "relationship": "BelongsToMany",
      "validations": []
    }],
    "segments": [],
    "actions": []
  }, {
    "name": "syliusProductAttribute",
    "nameOld": "syliusProductAttribute",
    "icon": null,
    "integration": null,
    "isReadOnly": false,
    "isSearchable": true,
    "isVirtual": false,
    "onlyForRelationships": false,
    "paginationType": "page",
    "fields": [{
      "field": "id",
      "type": "Number",
      "defaultValue": null,
      "enums": null,
      "integration": null,
      "isFilterable": true,
      "isPrimaryKey": true,
      "isReadOnly": false,
      "isRequired": false,
      "isSortable": true,
      "isVirtual": false,
      "reference": null,
      "inverseOf": null,
      "validations": []
    }, {
      "field": "name",
      "type": "String",
      "defaultValue": null,
      "enums": null,
      "integration": null,
      "isFilterable": true,
      "isPrimaryKey": false,
      "isReadOnly": false,
      "isRequired": true,
      "isSortable": true,
      "isVirtual": false,
      "reference": null,
      "inverseOf": null,
      "validations": [{
        "message": null,
        "type": "is present",
        "value": null
      }]
    }, {
      "field": "type",
      "type": "String",
      "defaultValue": null,
      "enums": null,
      "integration": null,
      "isFilterable": true,
      "isPrimaryKey": false,
      "isReadOnly": false,
      "isRequired": true,
      "isSortable": true,
      "isVirtual": false,
      "reference": null,
      "inverseOf": null,
      "validations": [{
        "message": null,
        "type": "is present",
        "value": null
      }]
    }],
    "segments": [],
    "actions": []
  }, {
    "name": "syliusProductTaxon",
    "nameOld": "syliusProductTaxon",
    "icon": null,
    "integration": null,
    "isReadOnly": false,
    "isSearchable": true,
    "isVirtual": false,
    "onlyForRelationships": false,
    "paginationType": "page",
    "fields": [{
      "field": "product",
      "type": "Number",
      "defaultValue": null,
      "enums": null,
      "integration": null,
      "isFilterable": true,
      "isPrimaryKey": false,
      "isReadOnly": false,
      "isRequired": false,
      "isSortable": true,
      "isVirtual": false,
      "reference": "syliusProduct.id",
      "inverseOf": null,
      "relationship": "BelongsTo",
      "validations": [],
      "foreignAndPrimaryKey": true
    }, {
      "field": "productId",
      "type": "Number",
      "defaultValue": null,
      "enums": null,
      "integration": null,
      "isFilterable": true,
      "isPrimaryKey": true,
      "isReadOnly": false,
      "isRequired": true,
      "isSortable": true,
      "isVirtual": false,
      "reference": null,
      "inverseOf": null,
      "validations": [{
        "message": null,
        "type": "is present",
        "value": null
      }]
    }, {
      "field": "taxon",
      "type": "Number",
      "defaultValue": null,
      "enums": null,
      "integration": null,
      "isFilterable": true,
      "isPrimaryKey": false,
      "isReadOnly": false,
      "isRequired": false,
      "isSortable": true,
      "isVirtual": false,
      "reference": "syliusTaxon.id",
      "inverseOf": null,
      "relationship": "BelongsTo",
      "validations": [],
      "foreignAndPrimaryKey": true
    }, {
      "field": "taxonId",
      "type": "Number",
      "defaultValue": null,
      "enums": null,
      "integration": null,
      "isFilterable": true,
      "isPrimaryKey": true,
      "isReadOnly": false,
      "isRequired": true,
      "isSortable": true,
      "isVirtual": false,
      "reference": null,
      "inverseOf": null,
      "validations": [{
        "message": null,
        "type": "is present",
        "value": null
      }]
    }],
    "segments": [],
    "actions": []
  }, {
    "name": "syliusProductVariant",
    "nameOld": "syliusProductVariant",
    "icon": null,
    "integration": null,
    "isReadOnly": false,
    "isSearchable": true,
    "isVirtual": false,
    "onlyForRelationships": false,
    "paginationType": "page",
    "fields": [{
      "field": "code",
      "type": "String",
      "defaultValue": null,
      "enums": null,
      "integration": null,
      "isFilterable": true,
      "isPrimaryKey": false,
      "isReadOnly": false,
      "isRequired": true,
      "isSortable": true,
      "isVirtual": false,
      "reference": null,
      "inverseOf": null,
      "validations": [{
        "message": null,
        "type": "is present",
        "value": null
      }]
    }, {
      "field": "id",
      "type": "Number",
      "defaultValue": null,
      "enums": null,
      "integration": null,
      "isFilterable": true,
      "isPrimaryKey": true,
      "isReadOnly": false,
      "isRequired": false,
      "isSortable": true,
      "isVirtual": false,
      "reference": null,
      "inverseOf": null,
      "validations": []
    }, {
      "field": "name",
      "type": "String",
      "defaultValue": null,
      "enums": null,
      "integration": null,
      "isFilterable": true,
      "isPrimaryKey": false,
      "isReadOnly": false,
      "isRequired": true,
      "isSortable": true,
      "isVirtual": false,
      "reference": null,
      "inverseOf": null,
      "validations": [{
        "message": null,
        "type": "is present",
        "value": null
      }]
    }, {
      "field": "price",
      "type": "Number",
      "defaultValue": null,
      "enums": null,
      "integration": null,
      "isFilterable": true,
      "isPrimaryKey": false,
      "isReadOnly": false,
      "isRequired": true,
      "isSortable": true,
      "isVirtual": false,
      "reference": null,
      "inverseOf": null,
      "validations": [{
        "message": null,
        "type": "is present",
        "value": null
      }]
    }, {
      "field": "product",
      "type": "Number",
      "defaultValue": null,
      "enums": null,
      "integration": null,
      "isFilterable": true,
      "isPrimaryKey": false,
      "isReadOnly": false,
      "isRequired": false,
      "isSortable": true,
      "isVirtual": false,
      "reference": "syliusProduct.id",
      "inverseOf": "productSyliusProductVariants",
      "relationship": "BelongsTo",
      "validations": []
    }],
    "segments": [],
    "actions": []
  }, {
    "name": "syliusShipping",
    "nameOld": "syliusShipping",
    "icon": null,
    "integration": null,
    "isReadOnly": false,
    "isSearchable": true,
    "isVirtual": false,
    "onlyForRelationships": false,
    "paginationType": "page",
    "fields": [{
      "field": "amount",
      "type": "Number",
      "defaultValue": null,
      "enums": null,
      "integration": null,
      "isFilterable": true,
      "isPrimaryKey": false,
      "isReadOnly": false,
      "isRequired": true,
      "isSortable": true,
      "isVirtual": false,
      "reference": null,
      "inverseOf": null,
      "validations": [{
        "message": null,
        "type": "is present",
        "value": null
      }]
    }, {
      "field": "id",
      "type": "Number",
      "defaultValue": null,
      "enums": null,
      "integration": null,
      "isFilterable": true,
      "isPrimaryKey": true,
      "isReadOnly": false,
      "isRequired": false,
      "isSortable": true,
      "isVirtual": false,
      "reference": null,
      "inverseOf": null,
      "validations": []
    }, {
      "field": "method",
      "type": "Number",
      "defaultValue": null,
      "enums": null,
      "integration": null,
      "isFilterable": true,
      "isPrimaryKey": false,
      "isReadOnly": false,
      "isRequired": false,
      "isSortable": true,
      "isVirtual": false,
      "reference": "syliusShippingMethod.id",
      "inverseOf": "methodSyliusShippings",
      "relationship": "BelongsTo",
      "validations": []
    }, {
      "field": "order",
      "type": "Number",
      "defaultValue": null,
      "enums": null,
      "integration": null,
      "isFilterable": true,
      "isPrimaryKey": false,
      "isReadOnly": false,
      "isRequired": false,
      "isSortable": true,
      "isVirtual": false,
      "reference": "syliusOrder.id",
      "inverseOf": "orderSyliusShippings",
      "relationship": "BelongsTo",
      "validations": []
    }, {
      "field": "state",
      "type": "String",
      "defaultValue": null,
      "enums": null,
      "integration": null,
      "isFilterable": true,
      "isPrimaryKey": false,
      "isReadOnly": false,
      "isRequired": true,
      "isSortable": true,
      "isVirtual": false,
      "reference": null,
      "inverseOf": null,
      "validations": [{
        "message": null,
        "type": "is present",
        "value": null
      }]
    }],
    "segments": [],
    "actions": []
  }, {
    "name": "syliusShippingMethod",
    "nameOld": "syliusShippingMethod",
    "icon": null,
    "integration": null,
    "isReadOnly": false,
    "isSearchable": true,
    "isVirtual": false,
    "onlyForRelationships": false,
    "paginationType": "page",
    "fields": [{
      "field": "calculator",
      "type": "String",
      "defaultValue": null,
      "enums": null,
      "integration": null,
      "isFilterable": true,
      "isPrimaryKey": false,
      "isReadOnly": false,
      "isRequired": true,
      "isSortable": true,
      "isVirtual": false,
      "reference": null,
      "inverseOf": null,
      "validations": [{
        "message": null,
        "type": "is present",
        "value": null
      }]
    }, {
      "field": "code",
      "type": "String",
      "defaultValue": null,
      "enums": null,
      "integration": null,
      "isFilterable": true,
      "isPrimaryKey": false,
      "isReadOnly": false,
      "isRequired": true,
      "isSortable": true,
      "isVirtual": false,
      "reference": null,
      "inverseOf": null,
      "validations": [{
        "message": null,
        "type": "is present",
        "value": null
      }]
    }, {
      "field": "description",
      "type": "String",
      "defaultValue": null,
      "enums": null,
      "integration": null,
      "isFilterable": true,
      "isPrimaryKey": false,
      "isReadOnly": false,
      "isRequired": false,
      "isSortable": true,
      "isVirtual": false,
      "reference": null,
      "inverseOf": null,
      "validations": []
    }, {
      "field": "id",
      "type": "Number",
      "defaultValue": null,
      "enums": null,
      "integration": null,
      "isFilterable": true,
      "isPrimaryKey": true,
      "isReadOnly": false,
      "isRequired": false,
      "isSortable": true,
      "isVirtual": false,
      "reference": null,
      "inverseOf": null,
      "validations": []
    }, {
      "field": "methodSyliusShippings",
      "type": ["Number"],
      "defaultValue": null,
      "enums": null,
      "integration": null,
      "isFilterable": true,
      "isPrimaryKey": false,
      "isReadOnly": false,
      "isRequired": false,
      "isSortable": true,
      "isVirtual": false,
      "reference": "syliusShipping.id",
      "inverseOf": "method",
      "relationship": "HasMany",
      "validations": []
    }, {
      "field": "name",
      "type": "String",
      "defaultValue": null,
      "enums": null,
      "integration": null,
      "isFilterable": true,
      "isPrimaryKey": false,
      "isReadOnly": false,
      "isRequired": true,
      "isSortable": true,
      "isVirtual": false,
      "reference": null,
      "inverseOf": null,
      "validations": [{
        "message": null,
        "type": "is present",
        "value": null
      }]
    }],
    "segments": [],
    "actions": []
  }, {
    "name": "syliusTaxon",
    "nameOld": "syliusTaxon",
    "icon": null,
    "integration": null,
    "isReadOnly": false,
    "isSearchable": true,
    "isVirtual": false,
    "onlyForRelationships": false,
    "paginationType": "page",
    "fields": [{
      "field": "description",
      "type": "String",
      "defaultValue": null,
      "enums": null,
      "integration": null,
      "isFilterable": true,
      "isPrimaryKey": false,
      "isReadOnly": false,
      "isRequired": false,
      "isSortable": true,
      "isVirtual": false,
      "reference": null,
      "inverseOf": null,
      "validations": []
    }, {
      "field": "id",
      "type": "Number",
      "defaultValue": null,
      "enums": null,
      "integration": null,
      "isFilterable": true,
      "isPrimaryKey": true,
      "isReadOnly": false,
      "isRequired": false,
      "isSortable": true,
      "isVirtual": false,
      "reference": null,
      "inverseOf": null,
      "validations": []
    }, {
      "field": "name",
      "type": "String",
      "defaultValue": null,
      "enums": null,
      "integration": null,
      "isFilterable": true,
      "isPrimaryKey": false,
      "isReadOnly": false,
      "isRequired": true,
      "isSortable": true,
      "isVirtual": false,
      "reference": null,
      "inverseOf": null,
      "validations": [{
        "message": null,
        "type": "is present",
        "value": null
      }]
    }, {
      "field": "syliusProductThroughSyliusProductTaxons",
      "type": ["Number"],
      "defaultValue": null,
      "enums": null,
      "integration": null,
      "isFilterable": true,
      "isPrimaryKey": false,
      "isReadOnly": false,
      "isRequired": false,
      "isSortable": true,
      "isVirtual": false,
      "reference": "syliusProduct.id",
      "inverseOf": "syliusTaxonThroughSyliusProductTaxons",
      "relationship": "BelongsToMany",
      "validations": []
    }],
    "segments": [],
    "actions": []
  }, {
    "name": "transaction",
    "nameOld": "transaction",
    "icon": null,
    "integration": null,
    "isReadOnly": false,
    "isSearchable": true,
    "isVirtual": false,
    "onlyForRelationships": false,
    "paginationType": "page",
    "fields": [{
      "field": "amount",
      "type": "Number",
      "defaultValue": null,
      "enums": null,
      "integration": null,
      "isFilterable": true,
      "isPrimaryKey": false,
      "isReadOnly": false,
      "isRequired": true,
      "isSortable": true,
      "isVirtual": false,
      "reference": null,
      "inverseOf": null,
      "validations": [{
        "message": null,
        "type": "is present",
        "value": null
      }]
    }, {
      "field": "createdAt",
      "type": "Date",
      "defaultValue": null,
      "enums": null,
      "integration": null,
      "isFilterable": true,
      "isPrimaryKey": false,
      "isReadOnly": false,
      "isRequired": false,
      "isSortable": true,
      "isVirtual": false,
      "reference": null,
      "inverseOf": null,
      "validations": []
    }, {
      "field": "customerIssue",
      "type": "Number",
      "defaultValue": null,
      "enums": null,
      "integration": null,
      "isFilterable": true,
      "isPrimaryKey": false,
      "isReadOnly": false,
      "isRequired": false,
      "isSortable": true,
      "isVirtual": false,
      "reference": "customerIssue.id",
      "inverseOf": "customerIssueTransaction",
      "relationship": "BelongsTo",
      "validations": []
    }, {
      "field": "deletedAt",
      "type": "Date",
      "defaultValue": null,
      "enums": null,
      "integration": null,
      "isFilterable": true,
      "isPrimaryKey": false,
      "isReadOnly": false,
      "isRequired": false,
      "isSortable": true,
      "isVirtual": false,
      "reference": null,
      "inverseOf": null,
      "validations": []
    }, {
      "field": "id",
      "type": "Number",
      "defaultValue": null,
      "enums": null,
      "integration": null,
      "isFilterable": true,
      "isPrimaryKey": true,
      "isReadOnly": false,
      "isRequired": false,
      "isSortable": true,
      "isVirtual": false,
      "reference": null,
      "inverseOf": null,
      "validations": []
    }, {
      "field": "order",
      "type": "Number",
      "defaultValue": null,
      "enums": null,
      "integration": null,
      "isFilterable": true,
      "isPrimaryKey": false,
      "isReadOnly": false,
      "isRequired": false,
      "isSortable": true,
      "isVirtual": false,
      "reference": "syliusOrder.id",
      "inverseOf": "orderTransaction",
      "relationship": "BelongsTo",
      "validations": []
    }, {
      "field": "status",
      "type": "Enum",
      "defaultValue": null,
      "enums": [
        "completed",
        "pending",
        "errored"
      ],
      "integration": null,
      "isFilterable": true,
      "isPrimaryKey": false,
      "isReadOnly": false,
      "isRequired": true,
      "isSortable": true,
      "isVirtual": false,
      "reference": null,
      "inverseOf": null,
      "validations": [{
        "message": null,
        "type": "is present",
        "value": null
      }]
    }, {
      "field": "type",
      "type": "Enum",
      "defaultValue": null,
      "enums": ["payment", "refund"],
      "integration": null,
      "isFilterable": true,
      "isPrimaryKey": false,
      "isReadOnly": false,
      "isRequired": true,
      "isSortable": true,
      "isVirtual": false,
      "reference": null,
      "inverseOf": null,
      "validations": [{
        "message": null,
        "type": "is present",
        "value": null
      }]
    }, {
      "field": "updatedAt",
      "type": "Date",
      "defaultValue": null,
      "enums": null,
      "integration": null,
      "isFilterable": true,
      "isPrimaryKey": false,
      "isReadOnly": false,
      "isRequired": false,
      "isSortable": true,
      "isVirtual": false,
      "reference": null,
      "inverseOf": null,
      "validations": []
    }],
    "segments": [],
    "actions": []
  }, {
    "name": "warehouse",
    "nameOld": "warehouse",
    "icon": null,
    "integration": null,
    "isReadOnly": false,
    "isSearchable": true,
    "isVirtual": false,
    "onlyForRelationships": false,
    "paginationType": "page",
    "fields": [{
      "field": "createdAt",
      "type": "Date",
      "defaultValue": null,
      "enums": null,
      "integration": null,
      "isFilterable": true,
      "isPrimaryKey": false,
      "isReadOnly": false,
      "isRequired": false,
      "isSortable": true,
      "isVirtual": false,
      "reference": null,
      "inverseOf": null,
      "validations": []
    }, {
      "field": "deletedAt",
      "type": "Date",
      "defaultValue": null,
      "enums": null,
      "integration": null,
      "isFilterable": true,
      "isPrimaryKey": false,
      "isReadOnly": false,
      "isRequired": false,
      "isSortable": true,
      "isVirtual": false,
      "reference": null,
      "inverseOf": null,
      "validations": []
    }, {
      "field": "id",
      "type": "Number",
      "defaultValue": null,
      "enums": null,
      "integration": null,
      "isFilterable": true,
      "isPrimaryKey": true,
      "isReadOnly": false,
      "isRequired": false,
      "isSortable": true,
      "isVirtual": false,
      "reference": null,
      "inverseOf": null,
      "validations": []
    }, {
      "field": "location",
      "type": "String",
      "defaultValue": null,
      "enums": null,
      "integration": null,
      "isFilterable": true,
      "isPrimaryKey": false,
      "isReadOnly": false,
      "isRequired": false,
      "isSortable": true,
      "isVirtual": false,
      "reference": null,
      "inverseOf": null,
      "validations": []
    }, {
      "field": "name",
      "type": "String",
      "defaultValue": null,
      "enums": null,
      "integration": null,
      "isFilterable": true,
      "isPrimaryKey": false,
      "isReadOnly": false,
      "isRequired": false,
      "isSortable": true,
      "isVirtual": false,
      "reference": null,
      "inverseOf": null,
      "validations": []
    }, {
      "field": "storageUnits",
      "type": ["Number"],
      "defaultValue": null,
      "enums": null,
      "integration": null,
      "isFilterable": true,
      "isPrimaryKey": false,
      "isReadOnly": false,
      "isRequired": false,
      "isSortable": true,
      "isVirtual": false,
      "reference": "storageUnit.id",
      "inverseOf": "warehouse",
      "relationship": "HasMany",
      "validations": []
    }, {
      "field": "surface",
      "type": "Number",
      "defaultValue": null,
      "enums": null,
      "integration": null,
      "isFilterable": true,
      "isPrimaryKey": false,
      "isReadOnly": false,
      "isRequired": true,
      "isSortable": true,
      "isVirtual": false,
      "reference": null,
      "inverseOf": null,
      "validations": [{
        "message": null,
        "type": "is present",
        "value": null
      }]
    }, {
      "field": "updatedAt",
      "type": "Date",
      "defaultValue": null,
      "enums": null,
      "integration": null,
      "isFilterable": true,
      "isPrimaryKey": false,
      "isReadOnly": false,
      "isRequired": false,
      "isSortable": true,
      "isVirtual": false,
      "reference": null,
      "inverseOf": null,
      "validations": []
    }],
    "segments": [],
    "actions": []
  }],
  "meta": {
    "liana": "forest-express-sequelize",
    "liana_version": "9.6.0",
    "stack": {
      "database_type": "mysql",
      "engine": "nodejs",
      "engine_version": "22.11.0",
      "orm_version": "5.15.2"
    }
  }
}